pystrfreq/__init__.py
pystrfreq/main.py
pystrfreq-0.3.2.dist-info/METADATA
pystrfreq-0.3.2.dist-info/WHEEL
pystrfreq-0.3.2.dist-info/entry_points.txt
pystrfreq-0.3.2.dist-info/licenses/LICENSE
pystrfreq-0.3.2.dist-info/RECORD
