Metadata-Version: 2.4
Name: pystrfreq
Version: 0.3.2
Summary: Tabulate the frequency of string object in a python codebase
Project-URL: Repository, https://github.com/plwg/pystrfreq
Author-email: plwg <56353330+plwg@users.noreply.github.com>
License-Expression: MIT
License-File: LICENSE
Keywords: ast,python,statistics,utility
Classifier: Development Status :: 4 - Beta
Classifier: Environment :: Console
Classifier: Operating System :: OS Independent
Classifier: Programming Language :: Python :: 3
Requires-Python: >=3.9
